tacky/__init__.py
tacky-0.0.32.dist-info/METADATA
tacky-0.0.32.dist-info/WHEEL
tacky-0.0.32.dist-info/entry_points.txt
tacky-0.0.32.dist-info/licenses/LICENSE
tacky-0.0.32.dist-info/RECORD
