Metadata-Version: 2.3
Name: tacky
Version: 0.0.32
Summary: a CLI to manage the macOS pasteboard
Author-email: Sasha F <cornflake.matchbox397@icantbelieveitsnotgmail.com>
Requires-Python: >=3.11
Requires-Dist: pyobjc-core>=10.3.2
Requires-Dist: pyobjc-framework-cocoa>=10.3.2
